Metadata-Version: 2.1
Name: cassandra-opentracing
Version: 0.0.5
Summary: OpenTracing support for Cassandra Driver
Home-page: UNKNOWN
Author: Nicholas Amorim
Author-email: nicholas@santos.ee
License: Apache License 2.0
Download-URL: https://github.com/nicholasamorim/opentracing-python-cassandra/tarball/0.0.5
Platform: any
Classifier: Intended Audience :: Developers
Classifier: License :: OSI Approved :: Apache Software License
Classifier: Operating System :: OS Independent
Classifier: Programming Language :: Python
Classifier: Topic :: Software Development :: Libraries :: Python Modules
Provides-Extra: tests
